triggercmd_cli/__init__.py
triggercmd_cli/__main__.py
triggercmd_cli/command/__init__.py
triggercmd_cli/command/command.py
triggercmd_cli/command/entities.py
triggercmd_cli/command/wizard.py
triggercmd_cli/main.py
triggercmd_cli/utils/__init__.py
triggercmd_cli/utils/constants.py
triggercmd_cli/utils/exceptions.py
triggercmd_cli/utils/functions.py
triggercmd-0.3.2.dist-info/entry_points.txt
triggercmd-0.3.2.dist-info/LICENSE
triggercmd-0.3.2.dist-info/WHEEL
triggercmd-0.3.2.dist-info/METADATA
triggercmd-0.3.2.dist-info/RECORD
