Metadata-Version: 2.1
Name: triggercmd
Version: 0.3.2
Summary: Linux CLI client to TriggerCMD cloud service agent.
Home-page: https://github.com/GussSoares/triggercmd-cli
License: MIT
Keywords: triggercmd,alexa,echo-dot,cli,archlinux,manjaro
Author: Gustavo Soares
Author-email: gustavo.soares.cdc@gmail.com
Requires-Python: >=3.7,<4.0
Classifier: License :: OSI Approved :: MIT License
Classifier: Operating System :: OS Independent
Classifier: Programming Language :: Python :: 3
Classifier: Programming Language :: Python :: 3.10
Classifier: Programming Language :: Python :: 3.7
Classifier: Programming Language :: Python :: 3.8
Classifier: Programming Language :: Python :: 3.9
Classifier: Topic :: Software Development :: Libraries :: Python Modules
Requires-Dist: inquirerpy (>=0.2.4,<0.3.0)
Requires-Dist: pyfiglet (>=0.8.post1,<0.9)
Requires-Dist: requests (>=2.26.0,<3.0.0)
Requires-Dist: rich (>=10.9.0,<11.0.0)
Requires-Dist: typer (==0.3.2)
Project-URL: Repository, https://github.com/GussSoares/triggercmd-cli
